tkwebview/__init__.py
tkwebview/core.py
tkwebview/test.py
tkwebview/platform/win32/x64/webview.dll
tkwebview/platform/win32/x86/webview.dll
tkwebview-0.3.0.dist-info/licenses/LICENSE
tkwebview-0.3.0.dist-info/METADATA
tkwebview-0.3.0.dist-info/WHEEL
tkwebview-0.3.0.dist-info/top_level.txt
tkwebview-0.3.0.dist-info/RECORD
