Metadata-Version: 2.4
Name: tkwebview
Version: 0.3.0
Summary: tkinter的webview视图
Home-page: https://github.com/Smart-Space/tkwebview
Author: Smart-Space
Author-email: smart-space@qq.com
License: MIT
Classifier: Programming Language :: Python :: 3
Classifier: License :: OSI Approved :: MIT License
Classifier: Operating System :: OS Independent
Requires-Python: >=3.7
License-File: LICENSE
Dynamic: author
Dynamic: author-email
Dynamic: classifier
Dynamic: description
Dynamic: description-content-type
Dynamic: home-page
Dynamic: license
Dynamic: license-file
Dynamic: requires-python
Dynamic: summary
